Metadata-Version: 1.0
Name: pydendroheatmap-kmyoo
Version: 0.1
Summary: Tool for creating heatmaps, where rows and columns are organized by hierarchical clusters
Home-page: https://github.com/kaniblu/dhm/
Author: Kang Min Yoo
Author-email: kaniblurous@gmail.com
License: MIT
Keywords: dendroheatmap dendrogram heatmap
Platform: UNKNOWN
